pypdtools/__init__.py
pypdtools/abc/__init__.py
pypdtools/abc/dataframe.py
pypdtools/abc/scripts.py
pypdtools/abc/services.py
pypdtools/core/__init__.py
pypdtools/core/dataframe.py
pypdtools/core/scripts.py
pypdtools/core/services/__init__.py
pypdtools/core/services/load_services.py
pypdtools/utils/__init__.py
pypdtools/utils/asyncs.py
pypdtools-0.0.5.dist-info/LICENSE
pypdtools-0.0.5.dist-info/METADATA
pypdtools-0.0.5.dist-info/WHEEL
pypdtools-0.0.5.dist-info/top_level.txt
pypdtools-0.0.5.dist-info/RECORD
