Metadata-Version: 2.1
Name: pypdtools
Version: 0.0.5
Summary: Package with tools for pandas
Author-email: Marciel Barcellos <marciel.barcellos@tcmrio.tc.br>
Project-URL: source, https://github.com/msbar/pypdtools
Project-URL: Documentation, https://msbar.github.io/pypdtools/
Project-URL: Bug Tracker, https://github.com/msbar/pypdtools/issues
Keywords: pandas,tools,asyncio
Classifier: Programming Language :: Python :: 3
Classifier: License :: OSI Approved :: MIT License
Classifier: Operating System :: OS Independent
Requires-Python: >=3.7
License-File: LICENSE
Requires-Dist: pandas (>=1.5.3)
Requires-Dist: openpyxl (>=3.1.2)
Requires-Dist: unidecode (>=1.3.6)
Provides-Extra: docs
Requires-Dist: mkdocs (==1.4.3) ; extra == 'docs'
Requires-Dist: mkdocs-material (==9.1.11) ; extra == 'docs'
Requires-Dist: mkdocstrings (==0.22.0) ; extra == 'docs'
Requires-Dist: mkdocstrings-python (==1.1.0) ; extra == 'docs'
Requires-Dist: pymdown-extensions (==9.11) ; extra == 'docs'
Provides-Extra: tests
Requires-Dist: anyio (==3.6.2) ; extra == 'tests'
Requires-Dist: black (==23.3.0) ; extra == 'tests'
Requires-Dist: isort (==5.12.0) ; extra == 'tests'
Requires-Dist: pytest (==7.3.1) ; extra == 'tests'
Requires-Dist: sqlalchemy (>=1.4.25) ; extra == 'tests'
